Main.py
SteamUser.py
SteamUser-0.0.4.dist-info/METADATA
SteamUser-0.0.4.dist-info/WHEEL
SteamUser-0.0.4.dist-info/top_level.txt
SteamUser-0.0.4.dist-info/RECORD
