Metadata-Version: 2.1
Name: SteamUser
Version: 0.0.4
Summary: Steam API for users
Home-page: UNKNOWN
Author: Fireblade2534
License: UNKNOWN
Platform: UNKNOWN
Classifier: Programming Language :: Python :: 3
Classifier: License :: OSI Approved :: MIT License
Classifier: Operating System :: OS Independent
Requires-Python: >=3.6
Requires-Dist: requests (>=2.28.1)
